AUTHORS
LICENSE
MANIFEST.in
README.rst
RELEASE-VERSION
setup.py
docs/background.rst
docs/glossary.rst
docs/netshark-api4.rst
docs/netshark.rst
docs/overview.rst
docs/settings.rst
docs/toc.rst
docs/tutorial.pcap
docs/tutorial.rst
examples/backup_restore.py
examples/cleanup_clips.py
examples/control_job.py
examples/create_clip.py
examples/create_job.py
examples/create_job_ex.py
examples/create_view.py
examples/create_view_ex.py
examples/download.py
examples/export.py
examples/list_netshark_sources.py
examples/netshark_scanner.py
examples/readview.py
examples/shark_info.py
examples/shark_upload_pcap.py
gitpy_versioning/__init__.py
notebooks/02-netshark-info.ipynb
notebooks/03-netshark-create-view.ipynb
notebooks/04-netshark-upload-pcap.ipynb
notebooks/05-netshark-analyze-pcap.ipynb
steelscript/__init__.py
steelscript.netshark.egg-info/PKG-INFO
steelscript.netshark.egg-info/SOURCES.txt
steelscript.netshark.egg-info/dependency_links.txt
steelscript.netshark.egg-info/entry_points.txt
steelscript.netshark.egg-info/namespace_packages.txt
steelscript.netshark.egg-info/requires.txt
steelscript.netshark.egg-info/top_level.txt
steelscript/netshark/__init__.py
steelscript/netshark/appfwk/__init__.py
steelscript/netshark/appfwk/models.py
steelscript/netshark/appfwk/plugin.py
steelscript/netshark/appfwk/datasources/__init__.py
steelscript/netshark/appfwk/datasources/netshark.py
steelscript/netshark/appfwk/datasources/netshark_msa.py
steelscript/netshark/appfwk/datasources/netshark_pcap.py
steelscript/netshark/appfwk/datasources/netshark_scanner_source.py
steelscript/netshark/appfwk/devices/__init__.py
steelscript/netshark/appfwk/devices/netshark.py
steelscript/netshark/appfwk/reports/__init__.py
steelscript/netshark/appfwk/reports/netshark.py
steelscript/netshark/appfwk/reports/netshark_dns.py
steelscript/netshark/appfwk/reports/netshark_jobs.py
steelscript/netshark/appfwk/reports/netshark_microburst.py
steelscript/netshark/appfwk/reports/netshark_microburst_tcp.py
steelscript/netshark/appfwk/reports/netshark_msa.py
steelscript/netshark/appfwk/reports/netshark_msa_report.py
steelscript/netshark/appfwk/reports/netshark_scanner_report.py
steelscript/netshark/appfwk/reports/netshark_tcp.py
steelscript/netshark/commands/__init__.py
steelscript/netshark/commands/fields.py
